cabot_alert_rocketchat/__init__.py
cabot_alert_rocketchat/models.py
cabot_alert_rocketchat/migrations/0001_initial.py
cabot_alert_rocketchat/migrations/__init__.py
cabot_alert_rocketchat-0.1.2.dist-info/LICENSE
cabot_alert_rocketchat-0.1.2.dist-info/METADATA
cabot_alert_rocketchat-0.1.2.dist-info/WHEEL
cabot_alert_rocketchat-0.1.2.dist-info/top_level.txt
cabot_alert_rocketchat-0.1.2.dist-info/RECORD
