Metadata-Version: 2.1
Name: cabot-alert-rocketchat
Version: 0.1.2
Summary: A RocketChat alert plugin for Cabot
Home-page: https://objectif-libre.com
Author: Objectif Libre
Author-email: flavien.hardy@objectif-libre.com
License: MIT
Platform: UNKNOWN
